{
  "project_info": {
    "project_number": "470987505252",
    "project_id": "hunter-fdc32",
    "storage_bucket": "hunter-fdc32.firebasestorage.app"
  },
  "client": [
    {
      "client_info": {
        "mobilesdk_app_id": "1:470987505252:android:fb197fdc662f971baf6971",
        "android_client_info": {
          "package_name": "com.ntou01157.hunter"
        }
      },
      "oauth_client": [
        {
          "client_id": "470987505252-1uvqfu2udjattd4nh3rq3kletd207q6n.apps.googleusercontent.com",
          "client_type": 1,
          "android_info": {
            "package_name": "com.ntou01157.hunter",
            "certificate_hash": "74c70a18aa88f1ffca269fe9cedc1a2503146b57"
          }
        },
        {
          "client_id": "470987505252-prcaeplvh2fe6mulm2apekf0g2amlloe.apps.googleusercontent.com",
          "client_type": 1,
          "android_info": {
            "package_name": "com.ntou01157.hunter",
            "certificate_hash": "2c7595da25af5700bb666d9f255fb0e654db3481"
          }
        },
        {
          "client_id": "470987505252-bu4vfgd774sa3mn9ranqu1r3an4kl2g5.apps.googleusercontent.com",
          "client_type": 3
        }
      ],
      "api_key": [
        {
          "current_key": "AIzaSyAQJI9ka2c73q7yh6Q3MUgEBUizZ412Ggc"
        }
      ],
      "services": {
        "appinvite_service": {
          "other_platform_oauth_client": [
            {
              "client_id": "470987505252-bu4vfgd774sa3mn9ranqu1r3an4kl2g5.apps.googleusercontent.com",
              "client_type": 3
            }
          ]
        }
      }
    }
  ],
  "configuration_version": "1"
}